exhibiter/__init__.py
exhibiter/cli.py
exhibiter/gui.py
exhibiter/template.docx
exhibiter-1.1.0.dist-info/LICENSE.md
exhibiter-1.1.0.dist-info/METADATA
exhibiter-1.1.0.dist-info/WHEEL
exhibiter-1.1.0.dist-info/entry_points.txt
exhibiter-1.1.0.dist-info/top_level.txt
exhibiter-1.1.0.dist-info/RECORD
