Metadata-Version: 2.1
Name: exhibiter
Version: 1.1.0
Summary: a tool to organize evidence for litigation
Home-page: https://github.com/raindrum/exhibiter
Author: Simon Raindrum Sherred
Author-email: simonraindrum@gmail.com
License: Non-Eviction
Platform: UNKNOWN
Classifier: License :: Free To Use But Restricted
Classifier: Development Status :: 4 - Beta
Classifier: Intended Audience :: Legal Industry
Classifier: Programming Language :: Python :: 3.8
Classifier: Environment :: Console
Classifier: Environment :: Other Environment
Classifier: Operating System :: OS Independent
License-File: LICENSE.md
Requires-Dist: pdfrw
Requires-Dist: pillow
Requires-Dist: reportlab
Requires-Dist: python-docx
Requires-Dist: PySide2
